{"P4": {"labels": ["Tools"], "postTitle": "\u56fe\u7247\u6df7\u5408\u7ed8\u5236", "postUrl": "post/tu-pian-hun-he-hui-zhi.html", "createdDate": "2025-01-23", "dateLabelColor": "#0969da"}, "P3": {"labels": ["Tools"], "postTitle": "pdf\u8f6c\u56fe\u7247\u5de5\u5177", "postUrl": "post/pdf-zhuan-tu-pian-gong-ju.html", "createdDate": "2025-01-23", "dateLabelColor": "#0969da"}, "P2": {"labels": ["Docker"], "postTitle": "Docker \u4f7f\u7528", "postUrl": "post/Docker%20-shi-yong.html", "createdDate": "2025-01-20", "dateLabelColor": "#0969da"}, "P1": {"labels": ["Docker"], "postTitle": "Docker \u5b89\u88c5", "postUrl": "post/Docker%20-an-zhuang.html", "createdDate": "2025-01-20", "dateLabelColor": "#0969da"}, "labelColorDict": {"Docker": "#e99695", "Tools": "#fbca04"}}